jinhui_mypython/__init__.py
jinhui_mypython/__version__.py
jinhui_mypython/core.py
jinhui_mypython-0.3.2.dist-info/LICENSE
jinhui_mypython-0.3.2.dist-info/METADATA
jinhui_mypython-0.3.2.dist-info/WHEEL
jinhui_mypython-0.3.2.dist-info/top_level.txt
jinhui_mypython-0.3.2.dist-info/RECORD
