Metadata-Version: 2.1
Name: jinhui-mypython
Version: 0.3.2
Summary: jinhui_mypython description
Home-page: https://github.com/zzz5323381/mypython
Author: jinhuizhuang
Author-email: 644471937@qq.com
License: MIT
Classifier: License :: OSI Approved :: MIT License
Classifier: Programming Language :: Python
Classifier: Programming Language :: Python :: 3
Classifier: Programming Language :: Python :: 3.6
Classifier: Programming Language :: Python :: Implementation :: CPython
Classifier: Programming Language :: Python :: Implementation :: PyPy
Requires-Python: >=3.6.0
License-File: LICENSE
